laia/__init__.py
laia/callbacks/__init__.py
laia/callbacks/decode.py
laia/callbacks/learning_rate.py
laia/callbacks/netout.py
laia/callbacks/progress_bar.py
laia/callbacks/progress_bar_gpu_stats.py
laia/callbacks/segmentation.py
laia/callbacks/training_timer.py
laia/callbacks/meters/__init__.py
laia/callbacks/meters/meter.py
laia/callbacks/meters/sequence_error.py
laia/callbacks/meters/timer.py
laia/common/__init__.py
laia/common/arguments.py
laia/common/loader.py
laia/common/logging.py
laia/common/saver.py
laia/common/types.py
laia/data/__init__.py
laia/data/image_dataset.py
laia/data/image_from_list_dataset.py
laia/data/padding_collater.py
laia/data/text_image_dataset.py
laia/data/text_image_from_text_table_dataset.py
laia/data/unpadded_distributed_sampler.py
laia/data/transforms/__init__.py
laia/data/transforms/transforms.py
laia/data/transforms/text/__init__.py
laia/data/transforms/text/transforms.py
laia/data/transforms/vision/__init__.py
laia/data/transforms/vision/random_beta_affine.py
laia/data/transforms/vision/random_beta_morphology.py
laia/data/transforms/vision/random_beta_perspective.py
laia/data/transforms/vision/transforms.py
laia/decoders/__init__.py
laia/decoders/ctc_alignment.py
laia/decoders/ctc_greedy_decoder.py
laia/decoders/ctc_language_decoder.py
laia/decoders/ctc_nbest_decoder.py
laia/dummies/__init__.py
laia/dummies/dummy_model.py
laia/dummies/dummy_plugin.py
laia/dummies/dummy_trainer.py
laia/dummies/data_modules/__init__.py
laia/dummies/data_modules/dummy_mnist.py
laia/dummies/data_modules/dummy_mnist_lines.py
laia/dummies/modules/__init__.py
laia/dummies/modules/dummy_engine.py
laia/dummies/modules/dummy_evaluator.py
laia/engine/__init__.py
laia/engine/data_module.py
laia/engine/engine_exception.py
laia/engine/engine_module.py
laia/engine/evaluator_module.py
laia/engine/feeder.py
laia/engine/htr_engine_module.py
laia/loggers/__init__.py
laia/loggers/epoch_csv_logger.py
laia/losses/__init__.py
laia/losses/ctc_loss.py
laia/losses/loss.py
pylaia-1.1.2.dist-info/LICENSE
pylaia-1.1.2.dist-info/METADATA
pylaia-1.1.2.dist-info/WHEEL
pylaia-1.1.2.dist-info/entry_points.txt
pylaia-1.1.2.dist-info/top_level.txt
pylaia-1.1.2.dist-info/RECORD
