Metadata-Version: 2.1
Name: pylaia
Version: 1.1.2
Author-email: Joan Puigcerver <joapuipe@gmail.com>
Maintainer-email: Teklia <contact@teklia.com>
License: MIT
Project-URL: Homepage, https://atr.pages.teklia.com/pylaia/
Project-URL: Downloads, https://gitlab.teklia.com/atr/pylaia
Project-URL: Documentation, https://atr.pages.teklia.com/pylaia/
Project-URL: Source, https://gitlab.teklia.com/atr/pylaia/
Project-URL: Tracker, https://gitlab.teklia.com/atr/pylaia/issues/
Keywords: HTR OCR python
Classifier: Development Status :: 5 - Production/Stable
Classifier: License :: OSI Approved :: MIT License
Classifier: Programming Language :: Python :: 3 :: Only
Classifier: Programming Language :: Python :: 3.10
Classifier: Programming Language :: Python :: 3.9
Classifier: Topic :: Scientific/Engineering :: Artificial Intelligence
Classifier: Topic :: Scientific/Engineering :: Image Recognition
Classifier: Topic :: Text Processing :: Linguistic
Requires-Python: <3.11,>=3.9
License-File: LICENSE
Requires-Dist: imagesize ==1.4.1
Requires-Dist: jsonargparse[signatures] ==4.7
Requires-Dist: matplotlib ==3.9.2
Requires-Dist: natsort ==8.4.0
Requires-Dist: pytorch-lightning ==1.4.2
Requires-Dist: scipy ==1.11.3
Requires-Dist: textdistance ==4.6.3
Requires-Dist: torch <1.14,>=1.13
Requires-Dist: torchaudio <0.14,>=0.13
Requires-Dist: torchmetrics <0.8.0
Requires-Dist: torchvision <0.15,>=0.14
Requires-Dist: mdutils ==1.6.0
Requires-Dist: prettytable ==3.11.0
Requires-Dist: python-bidi ==0.6.0
Provides-Extra: dev
Requires-Dist: pre-commit ==3.8.0 ; extra == 'dev'
Provides-Extra: docs
Requires-Dist: black ==24.8.0 ; extra == 'docs'
Requires-Dist: mkdocs-autorefs ==1.1.0 ; extra == 'docs'
Requires-Dist: mkdocs-gen-files ==0.5.0 ; extra == 'docs'
Requires-Dist: mkdocs-literate-nav ==0.6.1 ; extra == 'docs'
Requires-Dist: mkdocs-material ==9.5.33 ; extra == 'docs'
Requires-Dist: mkdocs-section-index ==0.3.9 ; extra == 'docs'
Requires-Dist: mkdocstrings-python ==1.10.8 ; extra == 'docs'
Provides-Extra: test
Requires-Dist: tox ==4.18.0 ; extra == 'test'
